svd_imputer/__init__.py
svd_imputer/_version.py
svd_imputer/imputer.py
svd_imputer/preprocessing.py
svd_imputer-0.2.7.dist-info/METADATA
svd_imputer-0.2.7.dist-info/WHEEL
svd_imputer-0.2.7.dist-info/top_level.txt
svd_imputer-0.2.7.dist-info/RECORD
