Metadata-Version: 2.4
Name: svd-imputer
Version: 0.2.7
Summary: SVD-based time series imputation with uncertainty estimation
Author: Rui Hugman
Maintainer: Rui Hugman
License-Expression: MIT
Project-URL: Homepage, https://github.com/rhugman/svd_imputer
Project-URL: Documentation, https://svd-imputer.readthedocs.io/
Project-URL: Repository, https://github.com/rhugman/svd_imputer.git
Project-URL: Bug Tracker, https://github.com/rhugman/svd_imputer/issues
Keywords: time-series,imputation,svd,missing-data,uncertainty,monte-carlo
Classifier: Development Status :: 4 - Beta
Classifier: Intended Audience :: Science/Research
Classifier: Operating System :: OS Independent
Classifier: Programming Language :: Python :: 3
Classifier: Programming Language :: Python :: 3.8
Classifier: Programming Language :: Python :: 3.9
Classifier: Programming Language :: Python :: 3.10
Classifier: Programming Language :: Python :: 3.11
Classifier: Programming Language :: Python :: 3.12
Classifier: Topic :: Scientific/Engineering
Classifier: Topic :: Scientific/Engineering :: Mathematics
Requires-Python: >=3.8
Requires-Dist: numpy>=1.20.0
Requires-Dist: pandas>=1.3.0
Requires-Dist: scikit-learn>=1.0.0
Provides-Extra: dev
Requires-Dist: pytest>=7.0.0; extra == "dev"
Requires-Dist: pytest-cov>=4.0.0; extra == "dev"
Requires-Dist: pytest-xdist>=3.0.0; extra == "dev"
Requires-Dist: pytest-mock>=3.10.0; extra == "dev"
Requires-Dist: pytest-benchmark>=4.0.0; extra == "dev"
Requires-Dist: black>=23.0.0; extra == "dev"
Requires-Dist: isort>=5.12.0; extra == "dev"
Requires-Dist: flake8>=6.0.0; extra == "dev"
Requires-Dist: mypy>=1.0.0; extra == "dev"
Requires-Dist: bandit>=1.7.5; extra == "dev"
Requires-Dist: safety>=2.3.0; extra == "dev"
Requires-Dist: pre-commit>=3.0.0; extra == "dev"
Provides-Extra: docs
Requires-Dist: sphinx>=6.0.0; extra == "docs"
Requires-Dist: sphinx-rtd-theme>=1.2.0; extra == "docs"
Requires-Dist: nbsphinx>=0.9.0; extra == "docs"
Requires-Dist: sphinx-autodoc-typehints>=1.20.0; extra == "docs"
Requires-Dist: sphinx-copybutton>=0.5.0; extra == "docs"
Provides-Extra: test
Requires-Dist: pytest>=7.0.0; extra == "test"
Requires-Dist: pytest-cov>=4.0.0; extra == "test"
Requires-Dist: pytest-xdist>=3.0.0; extra == "test"
Requires-Dist: pytest-mock>=3.10.0; extra == "test"
Requires-Dist: pytest-benchmark>=4.0.0; extra == "test"
Provides-Extra: security
Requires-Dist: bandit>=1.7.5; extra == "security"
Requires-Dist: safety>=2.3.0; extra == "security"
Requires-Dist: pip-audit>=2.6.0; extra == "security"
Provides-Extra: all
Requires-Dist: svd-imputer[dev,docs,security,test]; extra == "all"
